Workbook

Sheet Raw_Data
A1: RAW DATA — Internet Café Customer Records (As Provided, Unmodified)
A2: Source: Case_5 — Internet Café Customer Analysis | 50 records
A4: Visit_ID | B4: Day | C4: Customer_Type | D4: Age | E4: Computer_Unit | F4: Usage_Hours | G4: Gaming | H4: Printing_Pages | I4: Food_Order | J4: Internet_Sales | K4: Other_Sales | L4: Total_Sales
A5: V5000 | B5: 1 | C5: Other | D5: 20 | E5: 29 | F5: 7 | G5: No | H5: 6 | I5: No | J5: 175 | K5: 30 | L5: 205
A6: V5001 | B6: 2 | C6: Student | D6: 18 | E6: 17 | F6: 2 | G6: No | H6: 0 | I6: Yes | J6: 50 | K6: 80 | L6: 130
A7: V5002 | B7: 3 | C7: Worker | D7: 42 | E7: 4 | F7: 4 | G7: Yes | H7: 10 | I7: No | J7: 100 | K7: 50 | L7: 150
A8: V5003 | B8: 4 | C8: Worker | D8: 28 | E8: 10 | F8: 3 | G8: No | H8: 6 | I8: No | J8: 75 | K8: 30 | L8: 105
A9: V5004 | B9: 5 | C9: Worker | D9: 22 | E9: 30 | F9: 6 | G9: Yes | H9: 2 | I9: No | J9: 150 | K9: 10 | L9: 160
A10: V5005 | B10: 6 | C10: Student | D10: 38 | E10: 4 | F10: 4 | G10: No | H10: 2 | I10: No | J10: 100 | K10: 10 | L10: 110
A11: V5006 | B11: 7 | C11: Student | D11: 28 | E11: 12 | F11: 4 | G11: No | H11: 8 | I11: No | J11: 100 | K11: 40 | L11: 140
A12: V5007 | B12: 8 | C12: Student | D12: 39 | E12: 22 | F12: 5 | G12: No | H12: 8 | I12: Yes | J12: 125 | K12: 120 | L12: 245
A13: V5008 | B13: 9 | C13: Worker | D13: 16 | E13: 24 | F13: 5 | G13: Yes | H13: 8 | I13: Yes | J13: 125 | K13: 120 | L13: 245
A14: V5009 | B14: 10 | C14: Worker | D14: 24 | E14: 23 | F14: 8 | G14: Yes | H14: 7 | I14: No | J14: 200 | K14: 35 | L14: 235
A15: V5010 | B15: 11 | C15: Other | D15: 28 | E15: 25 | F15: 7 | G15: No | H15: 9 | I15: Yes | J15: 175 | K15: 125 | L15: 300
A16: V5011 | B16: 12 | C16: Other | D16: 41 | E16: 21 | F16: 8 | G16: Yes | H16: 2 | I16: No | J16: 200 | K16: 10 | L16: 210
... A54: V5049 | B54: 50 | C54: Student | D54: 37 | E54: 28 | F54: 7 | G54: No | H54: 3 | I54: No | J54: 175 | K54: 15 | L54: 190

Sheet Cleaned_Data
A1: CLEANED DATA — Verified Working Dataset
A2: Task 1–2: Data inspected for missing values, invalid entries, and duplicate Visit IDs. Columns N–P below perform automated checks. See Data_Cleaning_Notes for the summary.
A4: Visit_ID | B4: Day | C4: Customer_Type | D4: Age | E4: Computer_Unit | F4: Usage_Hours | G4: Gaming | H4: Printing_Pages | I4: Food_Order | J4: Internet_Sales | K4: Other_Sales | L4: Total_Sales | M4: Day_of_Week | N4: Sales_Check | O4: Duplicate_Check | P4: Rank_Unique
A5: V5000 | B5: 1 | C5: Other | D5: 20 | E5: 29 | F5: 7 | G5: No | H5: 6 | I5: No | J5: 175 | K5: 30 | L5: 205 | M5: =CHOOSE(MOD(B5-1,7)+1,"Monday","Tuesday","Wednesday","Thursday","Friday","Saturday","Sunday") -> Monday | N5: =IF(J5+K5=L5,"OK","MISMATCH") -> OK | O5: =IF(COUNTIF($A$5:$A$54,A5)>1,"DUPLICATE","Unique") -> Unique | P5: =RANK(L5,Cleaned_Data!$L$5:$L$54,0)+COUNTIF(Cleaned_Data!$L$5:L5,L5)-1 -> 14
A6: V5001 | B6: 2 | C6: Student | D6: 18 | E6: 17 | F6: 2 | G6: No | H6: 0 | I6: Yes | J6: 50 | K6: 80 | L6: 130 | M6: =CHOOSE(MOD(B6-1,7)+1,"Monday","Tuesday","Wednesday","Thursday","Friday","Saturday","Sunday") -> Tuesday | N6: =IF(J6+K6=L6,"OK","MISMATCH") -> OK | O6: =IF(COUNTIF($A$5:$A$54,A6)>1,"DUPLICATE","Unique") -> Unique | P6: =RANK(L6,Cleaned_Data!$L$5:$L$54,0)+COUNTIF(Cleaned_Data!$L$5:L6,L6)-1 -> 36
A7: V5002 | B7: 3 | C7: Worker | D7: 42 | E7: 4 | F7: 4 | G7: Yes | H7: 10 | I7: No | J7: 100 | K7: 50 | L7: 150 | M7: =CHOOSE(MOD(B7-1,7)+1,"Monday","Tuesday","Wednesday","Thursday","Friday","Saturday","Sunday") -> Wednesday | N7: =IF(J7+K7=L7,"OK","MISMATCH") -> OK | O7: =IF(COUNTIF($A$5:$A$54,A7)>1,"DUPLICATE","Unique") -> Unique | P7: =RANK(L7,Cleaned_Data!$L$5:$L$54,0)+COUNTIF(Cleaned_Data!$L$5:L7,L7)-1 -> 30
A8: V5003 | B8: 4 | C8: Worker | D8: 28 | E8: 10 | F8: 3 | G8: No | H8: 6 | I8: No | J8: 75 | K8: 30 | L8: 105 | M8: =CHOOSE(MOD(B8-1,7)+1,"Monday","Tuesday","Wednesday","Thursday","Friday","Saturday","Sunday") -> Thursday | N8: =IF(J8+K8=L8,"OK","MISMATCH") -> OK | O8: =IF(COUNTIF($A$5:$A$54,A8)>1,"DUPLICATE","Unique") -> Unique | P8: =RANK(L8,Cleaned_Data!$L$5:$L$54,0)+COUNTIF(Cleaned_Data!$L$5:L8,L8)-1 -> 41
A9: V5004 | B9: 5 | C9: Worker | D9: 22 | E9: 30 | F9: 6 | G9: Yes | H9: 2 | I9: No | J9: 150 | K9: 10 | L9: 160 | M9: =CHOOSE(MOD(B9-1,7)+1,"Monday","Tuesday","Wednesday","Thursday","Friday","Saturday","Sunday") -> Friday | N9: =IF(J9+K9=L9,"OK","MISMATCH") -> OK | O9: =IF(COUNTIF($A$5:$A$54,A9)>1,"DUPLICATE","Unique") -> Unique | P9: =RANK(L9,Cleaned_Data!$L$5:$L$54,0)+COUNTIF(Cleaned_Data!$L$5:L9,L9)-1 -> 24
A10: V5005 | B10: 6 | C10: Student | D10: 38 | E10: 4 | F10: 4 | G10: No | H10: 2 | I10: No | J10: 100 | K10: 10 | L10: 110 | M10: =CHOOSE(MOD(B10-1,7)+1,"Monday","Tuesday","Wednesday","Thursday","Friday","Saturday","Sunday") -> Saturday | N10: =IF(J10+K10=L10,"OK","MISMATCH") -> OK | O10: =IF(COUNTIF($A$5:$A$54,A10)>1,"DUPLICATE","Unique") -> Unique | P10: =RANK(L10,Cleaned_Data!$L$5:$L$54,0)+COUNTIF(Cleaned_Data!$L$5:L10,L10)-1 -> 40
A11: V5006 | B11: 7 | C11: Student | D11: 28 | E11: 12 | F11: 4 | G11: No | H11: 8 | I11: No | J11: 100 | K11: 40 | L11: 140 | M11: =CHOOSE(MOD(B11-1,7)+1,"Monday","Tuesday","Wednesday","Thursday","Friday","Saturday","Sunday") -> Sunday | N11: =IF(J11+K11=L11,"OK","MISMATCH") -> OK | O11: =IF(COUNTIF($A$5:$A$54,A11)>1,"DUPLICATE","Unique") -> Unique | P11: =RANK(L11,Cleaned_Data!$L$5:$L$54,0)+COUNTIF(Cleaned_Data!$L$5:L11,L11)-1 -> 33
A12: V5007 | B12: 8 | C12: Student | D12: 39 | E12: 22 | F12: 5 | G12: No | H12: 8 | I12: Yes | J12: 125 | K12: 120 | L12: 245 | M12: =CHOOSE(MOD(B12-1,7)+1,"Monday","Tuesday","Wednesday","Thursday","Friday","Saturday","Sunday") -> Monday | N12: =IF(J12+K12=L12,"OK","MISMATCH") -> OK | O12: =IF(COUNTIF($A$5:$A$54,A12)>1,"DUPLICATE","Unique") -> Unique | P12: =RANK(L12,Cleaned_Data!$L$5:$L$54,0)+COUNTIF(Cleaned_Data!$L$5:L12,L12)-1 -> 5
A13: V5008 | B13: 9 | C13: Worker | D13: 16 | E13: 24 | F13: 5 | G13: Yes | H13: 8 | I13: Yes | J13: 125 | K13: 120 | L13: 245 | M13: =CHOOSE(MOD(B13-1,7)+1,"Monday","Tuesday","Wednesday","Thursday","Friday","Saturday","Sunday") -> Tuesday | N13: =IF(J13+K13=L13,"OK","MISMATCH") -> OK | O13: =IF(COUNTIF($A$5:$A$54,A13)>1,"DUPLICATE","Unique") -> Unique | P13: =RANK(L13,Cleaned_Data!$L$5:$L$54,0)+COUNTIF(Cleaned_Data!$L$5:L13,L13)-1 -> 6
A14: V5009 | B14: 10 | C14: Worker | D14: 24 | E14: 23 | F14: 8 | G14: Yes | H14: 7 | I14: No | J14: 200 | K14: 35 | L14: 235 | M14: =CHOOSE(MOD(B14-1,7)+1,"Monday","Tuesday","Wednesday","Thursday","Friday","Saturday","Sunday") -> Wednesday | N14: =IF(J14+K14=L14,"OK","MISMATCH") -> OK | O14: =IF(COUNTIF($A$5:$A$54,A14)>1,"DUPLICATE","Unique") -> Unique | P14: =RANK(L14,Cleaned_Data!$L$5:$L$54,0)+COUNTIF(Cleaned_Data!$L$5:L14,L14)-1 -> 9
A15: V5010 | B15: 11 | C15: Other | D15: 28 | E15: 25 | F15: 7 | G15: No | H15: 9 | I15: Yes | J15: 175 | K15: 125 | L15: 300 | M15: =CHOOSE(MOD(B15-1,7)+1,"Monday","Tuesday","Wednesday","Thursday","Friday","Saturday","Sunday") -> Thursday | N15: =IF(J15+K15=L15,"OK","MISMATCH") -> OK | O15: =IF(COUNTIF($A$5:$A$54,A15)>1,"DUPLICATE","Unique") -> Unique | P15: =RANK(L15,Cleaned_Data!$L$5:$L$54,0)+COUNTIF(Cleaned_Data!$L$5:L15,L15)-1 -> 1
A16: V5011 | B16: 12 | C16: Other | D16: 41 | E16: 21 | F16: 8 | G16: Yes | H16: 2 | I16: No | J16: 200 | K16: 10 | L16: 210 | M16: =CHOOSE(MOD(B16-1,7)+1,"Monday","Tuesday","Wednesday","Thursday","Friday","Saturday","Sunday") -> Friday | N16: =IF(J16+K16=L16,"OK","MISMATCH") -> OK | O16: =IF(COUNTIF($A$5:$A$54,A16)>1,"DUPLICATE","Unique") -> Unique | P16: =RANK(L16,Cleaned_Data!$L$5:$L$54,0)+COUNTIF(Cleaned_Data!$L$5:L16,L16)-1 -> 13
... A54: V5049 | B54: 50 | C54: Student | D54: 37 | E54: 28 | F54: 7 | G54: No | H54: 3 | I54: No | J54: 175 | K54: 15 | L54: 190 | M54: =CHOOSE(MOD(B54-1,7)+1,"Monday","Tuesday","Wednesday","Thursday","Friday","Saturday","Sunday") -> Monday | N54: =IF(J54+K54=L54,"OK","MISMATCH") -> OK | O54: =IF(COUNTIF($A$5:$A$54,A54)>1,"DUPLICATE","Unique") -> Unique | P54: =RANK(L54,Cleaned_Data!$L$5:$L$54,0)+COUNTIF(Cleaned_Data!$L$5:L54,L54)-1 -> 18

Sheet Data_Cleaning_Notes
A1: TASK 1–2: DATA INSPECTION & CLEANING SUMMARY
A3: A. Completeness & Validity Check
A4: Total records inspected | C4: =COUNTA(Cleaned_Data!$A$5:$A$54) -> 50
A5: Missing values found (all fields) | C5: =COUNTBLANK(Cleaned_Data!A5:L54) -> 0
A6: Duplicate Visit IDs found | C6: =COUNTIF(Cleaned_Data!$O$5:$O$54,"DUPLICATE") -> 0
A7: Sales calculation mismatches (Internet+Other ≠ Total) | C7: =COUNTIF(Cleaned_Data!$N$5:$N$54,"MISMATCH") -> 0
A8: Negative or invalid Usage Hours found | C8: =COUNTIF(Cleaned_Data!$F$5:$F$54,"<0") -> 0
A9: Negative or invalid Age values found | C9: =COUNTIF(Cleaned_Data!$D$5:$D$54,"<10")+COUNTIF(Cleaned_Data!$D$5:$D$54,">100") -> 0
A10: Negative Printing Pages found | C10: =COUNTIF(Cleaned_Data!$H$5:$H$54,"<0") -> 0
A12: B. Conclusion
A13: ="After inspecting all "&C4&" records: "&C5&" missing values, "&C6&" duplicate Visit IDs, "&C7&" sales mismatches, and "&C8&" invalid Usage Hours or Age entries were found. The dataset is complete, internally consistent, and ready for analysis without further correction." -> After inspecting all 50 records: 0 missing values, 0 duplicate Visit IDs, 0 sales mismatches, and 0 invalid Usage Hours or Age entries were found. The dataset is complete, internally consistent, and ready for analysis without further correction.

Sheet Descriptive_Stats
A1: TASK 3–5: DESCRIPTIVE STATISTICS
A3: A. Usage Hours & Total Sales — Central Tendency and Range
A4: Metric | B4: Mean | C4: Median | D4: Minimum | E4: Maximum
A5: Usage Hours (per visit) | B5: =AVERAGE(Cleaned_Data!$F$5:$F$54) -> 4.9 | C5: =MEDIAN(Cleaned_Data!$F$5:$F$54) -> 5 | D5: =MIN(Cleaned_Data!$F$5:$F$54) -> 1 | E5: =MAX(Cleaned_Data!$F$5:$F$54) -> 8
A6: Total Sales (Php) | B6: =AVERAGE(Cleaned_Data!$L$5:$L$54) -> 166.9 | C6: =MEDIAN(Cleaned_Data!$L$5:$L$54) -> 160 | D6: =MIN(Cleaned_Data!$L$5:$L$54) -> 50 | E6: =MAX(Cleaned_Data!$L$5:$L$54) -> 300
A9: B. Overall Business Volume
A10: Total Number of Customer Visits | B10: =COUNTA(Cleaned_Data!$A$5:$A$54) -> 50
A11: Total Sales Generated (Php) | B11: =SUM(Cleaned_Data!$L$5:$L$54) -> 8345
A12: Average Sales per Customer Visit (Php) | B12: =B11/B10 -> 166.9
A15: C. Interpretation
A16: ="On average, customers use the computer for "&TEXT(B5,"0.0")&" hours per visit (range: "&D5&"–"&E5&" hours). Average spending per visit is Php "&TEXT(B12,"#,##0.00")&", and the café generated a total of Php "&TEXT(B11,"#,##0.00")&" in sales across "&B10&" visits. The spread between the minimum (Php "&TEXT(D6,"#,##0")&") and maximum (Php "&TEXT(E6,"#,##0")&") single-visit sale shows that a small number of high-value visits (likely longer usage or food/printing add-ons) pull the average upward relative to the median (Php "&TEXT(C6,"#,##0")&")." -> On average, customers use the computer for 4.9 hours per visit (range: 1–8 hours). Average spending per visit is Php 166.90, and the café generated a total of Php 8,345.00 in sales across 50 visits. The spread between the minimum (Php 50) and maximum (Php 300) single-visit sale shows that a small number of high-value visits (likely longer usage or food/printing add-ons) pull the average upward relative to the median (Php 160).

Sheet Customer_Type_Analysis
A1: TASK 6, 7 & 13: CUSTOMER TYPE ANALYSIS (PivotTable-style Summary)
A2: Summary built with COUNTIF/SUMIF/AVERAGEIF formulas against Cleaned_Data — functions as the required PivotTable summarizing Customer Type, Number of Visits, Usage Hours, and Total Sales.
A4: Customer Type | B4: Number of Visits | C4: Total Usage Hours | D4: Avg Usage Hours | E4: Total Sales (Php) | F4: Avg Sales per Visit (Php)
A5: Student | B5: =COUNTIF(Cleaned_Data!$C$5:$C$54,A5) -> 20 | C5: =SUMIF(Cleaned_Data!$C$5:$C$54,A5,Cleaned_Data!$F$5:$F$54) -> 94 | D5: =C5/B5 -> 4.7 | E5: =SUMIF(Cleaned_Data!$C$5:$C$54,A5,Cleaned_Data!$L$5:$L$54) -> 3315 | F5: =E5/B5 -> 165.75
A6: Worker | B6: =COUNTIF(Cleaned_Data!$C$5:$C$54,A6) -> 15 | C6: =SUMIF(Cleaned_Data!$C$5:$C$54,A6,Cleaned_Data!$F$5:$F$54) -> 76 | D6: =C6/B6 -> 5.0666667 | E6: =SUMIF(Cleaned_Data!$C$5:$C$54,A6,Cleaned_Data!$L$5:$L$54) -> 2375 | F6: =E6/B6 -> 158.33333
A7: Other | B7: =COUNTIF(Cleaned_Data!$C$5:$C$54,A7) -> 15 | C7: =SUMIF(Cleaned_Data!$C$5:$C$54,A7,Cleaned_Data!$F$5:$F$54) -> 75 | D7: =C7/B7 -> 5 | E7: =SUMIF(Cleaned_Data!$C$5:$C$54,A7,Cleaned_Data!$L$5:$L$54) -> 2655 | F7: =E7/B7 -> 177
A8: TOTAL | B8: =SUM(B5:B7) -> 50 | C8: =SUM(C5:C7) -> 245 | D8: =C8/B8 -> 4.9 | E8: =SUM(E5:E7) -> 8345 | F8: =E8/B8 -> 166.9
A28: Interpretation
A29: ="Students make up the largest customer segment with "&B5&" visits, followed by Worker and Other customer types. "&INDEX(A5:A7,MATCH(MAX(E5:E7),E5:E7,0))&" customers generate the highest total sales (Php "&TEXT(MAX(E5:E7),"#,##0")&"), while "&INDEX(A5:A7,MATCH(MAX(F5:F7),F5:F7,0))&" customers spend the most per visit on average (Php "&TEXT(MAX(F5:F7),"#,##0.00")&"). This suggests the café should tailor promotions differently for each segment — e.g., bundled study-hour rates for students versus premium/priority service for the higher-spending segment." -> Students make up the largest customer segment with 20 visits, followed by Worker and Other customer types. Student customers generate the highest total sales (Php 3,315), while Other customers spend the most per visit on average (Php 177.00). This suggests the café should tailor promotions differently for each segment — e.g., bundled study-hour rates for students versus premium/priority service for the higher-spending segment.

Sheet Service_Analysis
A1: TASK 8–9: GAMING & PRINTING SERVICE ANALYSIS
A3: A. Gaming Service Usage
A4: Customers who used Gaming Service | B4: =COUNTIF(Cleaned_Data!$G$5:$G$54,"Yes") -> 22
A5: Customers who did NOT use Gaming Service | B5: =COUNTIF(Cleaned_Data!$G$5:$G$54,"No") -> 28
A6: % of Customers Using Gaming Service | B6: =B4/COUNTA(Cleaned_Data!$A$5:$A$54)*100 -> 44
A9: B. Printing Activity
A10: Total Number of Pages Printed | B10: =SUM(Cleaned_Data!$H$5:$H$54) -> 220
A11: Customers Who Printed (Pages > 0) | B11: =COUNTIF(Cleaned_Data!$H$5:$H$54,">0") -> 42
A12: Average Pages Printed per Visit | B12: =AVERAGE(Cleaned_Data!$H$5:$H$54) -> 4.4
A15: Interpretation
A16: ="Gaming Service is used in "&TEXT(B6,"0.0")&"% of visits ("&B4&" out of "&(B4+B5)&"), showing it is a popular but not dominant add-on. Printing is used by "&B11&" customers, totaling "&B10&" pages ("&TEXT(B12,"0.0")&" pages/visit on average) — this is a meaningful secondary revenue stream worth highlighting alongside internet time." -> Gaming Service is used in 44.0% of visits (22 out of 50), showing it is a popular but not dominant add-on. Printing is used by 42 customers, totaling 220 pages (4.4 pages/visit on average) — this is a meaningful secondary revenue stream worth highlighting alongside internet time.

Sheet Revenue_Sources
A1: TASK 10: INTERNET SALES vs. OTHER SALES
A3: Revenue Source | B3: Total Sales (Php) | C3: % of Total Revenue
A4: Internet Sales | B4: =SUM(Cleaned_Data!$J$5:$J$54) -> 6125 | C4: =B4/(B4+B5)*100 -> 73.397244
A5: Other Sales (Food, Printing, etc.) | B5: =SUM(Cleaned_Data!$K$5:$K$54) -> 2220 | C5: =B5/(B4+B5)*100 -> 26.602756
A6: TOTAL | B6: =SUM(B4:B5) -> 8345 | C6: =SUM(C4:C5) -> 100
A8: Major Revenue Source | B8: =IF(B4>B5,"Internet Sales","Other Sales") -> Internet Sales
A28: Interpretation
A29: ="Internet Sales is the primary revenue driver, contributing Php "&TEXT(B4,"#,##0")&" ("&TEXT(C4,"0.0")&"% of total revenue), compared to Php "&TEXT(B5,"#,##0")&" ("&TEXT(C5,"0.0")&"%) from Other Sales (food, printing, and gaming add-ons combined). This indicates computer/internet rental time remains the café's core product, while other services act as valuable upsell opportunities rather than primary income." -> Internet Sales is the primary revenue driver, contributing Php 6,125 (73.4% of total revenue), compared to Php 2,220 (26.6%) from Other Sales (food, printing, and gaming add-ons combined). This indicates computer/internet rental time remains the café's core product, while other services act as valuable upsell opportunities rather than primary income.

Sheet Day_of_Week_Analysis
A1: TASK 11: SALES BY DAY OF THE WEEK
A2: Day 1 of the dataset is treated as Monday, cycling every 7 days through Day 50.
A4: Day of Week | B4: Number of Visits | C4: Total Sales (Php) | D4: Avg Sales per Visit (Php)
A5: Monday | B5: =COUNTIF(Cleaned_Data!$M$5:$M$54,A5) -> 8 | C5: =SUMIF(Cleaned_Data!$M$5:$M$54,A5,Cleaned_Data!$L$5:$L$54) -> 1490 | D5: =C5/B5 -> 186.25
A6: Tuesday | B6: =COUNTIF(Cleaned_Data!$M$5:$M$54,A6) -> 7 | C6: =SUMIF(Cleaned_Data!$M$5:$M$54,A6,Cleaned_Data!$L$5:$L$54) -> 995 | D6: =C6/B6 -> 142.14286
A7: Wednesday | B7: =COUNTIF(Cleaned_Data!$M$5:$M$54,A7) -> 7 | C7: =SUMIF(Cleaned_Data!$M$5:$M$54,A7,Cleaned_Data!$L$5:$L$54) -> 1290 | D7: =C7/B7 -> 184.28571
A8: Thursday | B8: =COUNTIF(Cleaned_Data!$M$5:$M$54,A8) -> 7 | C8: =SUMIF(Cleaned_Data!$M$5:$M$54,A8,Cleaned_Data!$L$5:$L$54) -> 1205 | D8: =C8/B8 -> 172.14286
A9: Friday | B9: =COUNTIF(Cleaned_Data!$M$5:$M$54,A9) -> 7 | C9: =SUMIF(Cleaned_Data!$M$5:$M$54,A9,Cleaned_Data!$L$5:$L$54) -> 1280 | D9: =C9/B9 -> 182.85714
A10: Saturday | B10: =COUNTIF(Cleaned_Data!$M$5:$M$54,A10) -> 7 | C10: =SUMIF(Cleaned_Data!$M$5:$M$54,A10,Cleaned_Data!$L$5:$L$54) -> 1035 | D10: =C10/B10 -> 147.85714
A11: Sunday | B11: =COUNTIF(Cleaned_Data!$M$5:$M$54,A11) -> 7 | C11: =SUMIF(Cleaned_Data!$M$5:$M$54,A11,Cleaned_Data!$L$5:$L$54) -> 1050 | D11: =C11/B11 -> 150
A12: Best Day (Total Sales) | B12: =INDEX(A5:A11,MATCH(MAX(C5:C11),C5:C11,0)) -> Monday
A13: Slowest Day (Total Sales) | B13: =INDEX(A5:A11,MATCH(MIN(C5:C11),C5:C11,0)) -> Tuesday
A34: Interpretation
A35: ="Sales peak on "&B12&" and are weakest on "&B13&". This pattern is useful for staffing and promotions — management can schedule more staff or run "&B12&" specials to capture peak demand, and run promos or discounts on "&B13&" to boost slow-day traffic." -> Sales peak on Monday and are weakest on Tuesday. This pattern is useful for staffing and promotions — management can schedule more staff or run Monday specials to capture peak demand, and run promos or discounts on Tuesday to boost slow-day traffic.

Sheet Top5_Transactions
A1: TASK 14: TOP 5 CUSTOMER TRANSACTIONS BY TOTAL SALES
A2: Ties are broken by original row order (Rank_Unique helper column in Cleaned_Data).
A4: Rank | B4: Visit ID | C4: Customer Type | D4: Usage Hours | E4: Total Sales (Php)
A5: 1 | B5: =INDEX(Cleaned_Data!$A$5:$A$54,MATCH(1,Cleaned_Data!$P$5:$P$54,0)) -> V5010 | C5: =INDEX(Cleaned_Data!$C$5:$C$54,MATCH(1,Cleaned_Data!$P$5:$P$54,0)) -> Other | D5: =INDEX(Cleaned_Data!$F$5:$F$54,MATCH(1,Cleaned_Data!$P$5:$P$54,0)) -> 7 | E5: =INDEX(Cleaned_Data!$L$5:$L$54,MATCH(1,Cleaned_Data!$P$5:$P$54,0)) -> 300
A6: 2 | B6: =INDEX(Cleaned_Data!$A$5:$A$54,MATCH(2,Cleaned_Data!$P$5:$P$54,0)) -> V5014 | C6: =INDEX(Cleaned_Data!$C$5:$C$54,MATCH(2,Cleaned_Data!$P$5:$P$54,0)) -> Student | D6: =INDEX(Cleaned_Data!$F$5:$F$54,MATCH(2,Cleaned_Data!$P$5:$P$54,0)) -> 8 | E6: =INDEX(Cleaned_Data!$L$5:$L$54,MATCH(2,Cleaned_Data!$P$5:$P$54,0)) -> 300
A7: 3 | B7: =INDEX(Cleaned_Data!$A$5:$A$54,MATCH(3,Cleaned_Data!$P$5:$P$54,0)) -> V5023 | C7: =INDEX(Cleaned_Data!$C$5:$C$54,MATCH(3,Cleaned_Data!$P$5:$P$54,0)) -> Other | D7: =INDEX(Cleaned_Data!$F$5:$F$54,MATCH(3,Cleaned_Data!$P$5:$P$54,0)) -> 7 | E7: =INDEX(Cleaned_Data!$L$5:$L$54,MATCH(3,Cleaned_Data!$P$5:$P$54,0)) -> 265
A8: 4 | B8: =INDEX(Cleaned_Data!$A$5:$A$54,MATCH(4,Cleaned_Data!$P$5:$P$54,0)) -> V5024 | C8: =INDEX(Cleaned_Data!$C$5:$C$54,MATCH(4,Cleaned_Data!$P$5:$P$54,0)) -> Other | D8: =INDEX(Cleaned_Data!$F$5:$F$54,MATCH(4,Cleaned_Data!$P$5:$P$54,0)) -> 6 | E8: =INDEX(Cleaned_Data!$L$5:$L$54,MATCH(4,Cleaned_Data!$P$5:$P$54,0)) -> 265
A9: 5 | B9: =INDEX(Cleaned_Data!$A$5:$A$54,MATCH(5,Cleaned_Data!$P$5:$P$54,0)) -> V5007 | C9: =INDEX(Cleaned_Data!$C$5:$C$54,MATCH(5,Cleaned_Data!$P$5:$P$54,0)) -> Student | D9: =INDEX(Cleaned_Data!$F$5:$F$54,MATCH(5,Cleaned_Data!$P$5:$P$54,0)) -> 5 | E9: =INDEX(Cleaned_Data!$L$5:$L$54,MATCH(5,Cleaned_Data!$P$5:$P$54,0)) -> 245
A12: Interpretation
A13: ="The top 5 transactions range from Php "&TEXT(E9,"#,##0")&" to Php "&TEXT(E5,"#,##0")&", well above the overall average visit value. These high-value visits share longer usage hours and/or combine internet time with food and printing add-ons, confirming that bundling services increases per-visit revenue." -> The top 5 transactions range from Php 245 to Php 300, well above the overall average visit value. These high-value visits share longer usage hours and/or combine internet time with food and printing add-ons, confirming that bundling services increases per-visit revenue.

Sheet Correlation_Analysis
A1: TASK 15: CORRELATION — USAGE HOURS vs. TOTAL SALES
A3: Correlation Coefficient (r) | B3: =CORREL(Cleaned_Data!$F$5:$F$54,Cleaned_Data!$L$5:$L$54) -> 0.79109481
A4: Strength of Relationship | B4: =IF(ABS(B3)>=0.7,"Strong",IF(ABS(B3)>=0.4,"Moderate",IF(ABS(B3)>=0.1,"Weak","Negligible"))) -> Strong
A5: Direction | B5: =IF(B3>0,"Positive","Negative") -> Positive
A34: Interpretation
A35: ="A correlation of "&TEXT(B3,"0.000")&" indicates a "&LOWER(B4)&", "&LOWER(B5)&" relationship between Usage Hours and Total Sales. In practical terms, customers who stay longer on the computer tend to spend more overall — likely because longer sessions increase the chance of add-on purchases like food, printing, or gaming. This supports promoting hourly package deals or loyalty discounts for longer sessions to increase average spend per visit." -> A correlation of 0.791 indicates a strong, positive relationship between Usage Hours and Total Sales. In practical terms, customers who stay longer on the computer tend to spend more overall — likely because longer sessions increase the chance of add-on purchases like food, printing, or gaming. This supports promoting hourly package deals or loyalty discounts for longer sessions to increase average spend per visit.

Sheet Recommendations
A1: FINDINGS & RECOMMENDATIONS
A3: Key Findings
A4: ="1. Students are the largest customer segment ("&Customer_Type_Analysis!B5&" of "&Customer_Type_Analysis!B8&" visits), but "&INDEX(Customer_Type_Analysis!A5:A7,MATCH(MAX(Customer_Type_Analysis!F5:F7),Customer_Type_Analysis!F5:F7,0))&" customers spend the most per visit on average (Php "&TEXT(MAX(Customer_Type_Analysis!F5:F7),"#,##0.00")&")." -> 1. Students are the largest customer segment (20 of 50 visits), but Other customers spend the most per visit on average (Php 177.00).
A5: ="2. Internet Sales is the dominant revenue source at "&TEXT(Revenue_Sources!C4,"0.0")&"% of total revenue, versus "&TEXT(Revenue_Sources!C5,"0.0")&"% from food, printing, and gaming combined." -> 2. Internet Sales is the dominant revenue source at 73.4% of total revenue, versus 26.6% from food, printing, and gaming combined.
A6: ="3. Sales peak on "&Day_of_Week_Analysis!B12&" and dip on "&Day_of_Week_Analysis!B13&", showing a clear weekly demand pattern." -> 3. Sales peak on Monday and dip on Tuesday, showing a clear weekly demand pattern.
A7: ="4. Usage Hours and Total Sales are positively correlated (r = "&TEXT(Correlation_Analysis!B3,"0.000")&"), meaning longer sessions reliably translate to higher spending." -> 4. Usage Hours and Total Sales are positively correlated (r = 0.791), meaning longer sessions reliably translate to higher spending.
A8: ="5. Gaming Service is used in "&TEXT(Service_Analysis!B6,"0.0")&"% of visits, and printing activity totals "&Service_Analysis!B10&" pages across "&Service_Analysis!B11&" customers — both are proven secondary revenue streams with room to grow." -> 5. Gaming Service is used in 44.0% of visits, and printing activity totals 220 pages across 42 customers — both are proven secondary revenue streams with room to grow.
A10: Evidence-Based Recommendations
A11: 1. Launch bundled hourly packages (internet time + food or printing credits) to capitalize on the positive correlation between usage hours and total sales — longer, bundled visits already spend more per visit.
A12: 2. Run targeted promotions on the slowest day of the week (see Day_of_Week_Analysis) — e.g., discounted rates or gaming-hour specials — to smooth out weekly demand and reduce idle computer time.
A13: 3. Develop loyalty or membership pricing for Worker and Other customer types, who spend more per visit than Students on average, while offering student-friendly study-hour bundles to retain the largest segment by volume.
A14: 4. Since Internet Sales dominates revenue, actively cross-sell food and printing at the counter during check-in/checkout to grow the Other Sales share, which currently trails well behind Internet Sales.
